aden/__init__.py
aden/call_stack.py
aden/content_capture.py
aden/content_storage.py
aden/control_agent.py
aden/control_types.py
aden/emitters.py
aden/file_logger.py
aden/http_transport.py
aden/instrument.py
aden/instrument_anthropic.py
aden/instrument_gemini.py
aden/instrument_gemini_grpc.py
aden/instrument_genai.py
aden/instrument_openai.py
aden/large_content.py
aden/livekit.py
aden/meter.py
aden/normalize.py
aden/py.typed
aden/schema_validator.py
aden/timescale.py
aden/tool_capture.py
aden/types.py
aden_py-0.4.2.dist-info/METADATA
aden_py-0.4.2.dist-info/WHEEL
aden_py-0.4.2.dist-info/RECORD
