Metadata-Version: 2.4
Name: aden-py
Version: 0.4.2
Summary: Multi-provider LLM SDK metering - OpenAI, Anthropic, Gemini - usage tracking, budget enforcement, and cost control
Project-URL: Homepage, https://github.com/aden/aden-py
Project-URL: Documentation, https://github.com/aden/aden-py#readme
Project-URL: Repository, https://github.com/aden/aden-py
Author-email: Aden <aden@example.com>
License-Expression: MIT
Keywords: anthropic,billing,cost,erp,gemini,livekit,llm,metering,openai,usage
Classifier: Development Status :: 4 - Beta
Classifier: Intended Audience :: Developers
Classifier: License :: OSI Approved :: MIT License
Classifier: Programming Language :: Python :: 3
Classifier: Programming Language :: Python :: 3.10
Classifier: Programming Language :: Python :: 3.11
Classifier: Programming Language :: Python :: 3.12
Classifier: Topic :: Software Development :: Libraries :: Python Modules
Requires-Python: >=3.10
Requires-Dist: aiohttp>=3.8.0
Requires-Dist: certifi>=2023.0.0
Requires-Dist: python-socketio[asyncio-client]>=5.10.0
Provides-Extra: adk
Requires-Dist: google-adk>=0.1.0; extra == 'adk'
Requires-Dist: google-genai>=1.0.0; extra == 'adk'
Provides-Extra: all
Requires-Dist: anthropic>=0.20.0; extra == 'all'
Requires-Dist: google-genai>=1.0.0; extra == 'all'
Requires-Dist: google-generativeai>=0.4.0; extra == 'all'
Requires-Dist: openai>=1.0.0; extra == 'all'
Requires-Dist: tiktoken>=0.5.0; extra == 'all'
Provides-Extra: anthropic
Requires-Dist: anthropic>=0.20.0; extra == 'anthropic'
Provides-Extra: dev
Requires-Dist: mypy>=1.0.0; extra == 'dev'
Requires-Dist: pytest-asyncio>=0.21.0; extra == 'dev'
Requires-Dist: pytest>=7.0.0; extra == 'dev'
Requires-Dist: python-dotenv>=1.0.0; extra == 'dev'
Requires-Dist: ruff>=0.1.0; extra == 'dev'
Provides-Extra: gemini
Requires-Dist: google-generativeai>=0.4.0; extra == 'gemini'
Provides-Extra: genai
Requires-Dist: google-genai>=1.0.0; extra == 'genai'
Provides-Extra: livekit
Requires-Dist: livekit-agents>=0.8.0; extra == 'livekit'
Requires-Dist: livekit-plugins-openai>=0.8.0; extra == 'livekit'
Requires-Dist: openai>=1.0.0; extra == 'livekit'
Requires-Dist: tiktoken>=0.5.0; extra == 'livekit'
Provides-Extra: openai
Requires-Dist: openai>=1.0.0; extra == 'openai'
Requires-Dist: tiktoken>=0.5.0; extra == 'openai'
Provides-Extra: pydantic-ai
Requires-Dist: openai>=1.0.0; extra == 'pydantic-ai'
Requires-Dist: pydantic-ai>=0.0.1; extra == 'pydantic-ai'
Provides-Extra: timescale
Requires-Dist: asyncpg>=0.29.0; extra == 'timescale'
Provides-Extra: timescale-sync
Requires-Dist: psycopg2-binary>=2.9.0; extra == 'timescale-sync'
